pipns/__init__.py
pipns/__main__.py
pipns/scripts/package_files.py
pipip-0.0.10.dist-info/LICENSE
pipip-0.0.10.dist-info/METADATA
pipip-0.0.10.dist-info/WHEEL
pipip-0.0.10.dist-info/entry_points.txt
pipip-0.0.10.dist-info/top_level.txt
pipip-0.0.10.dist-info/RECORD
